CHANGELOG.md
LICENSE
MANIFEST.in
README.md
pyproject.toml
setup.py
sensemapi/__init__.py
sensemapi/__main__.py
sensemapi/account.py
sensemapi/application.py
sensemapi/cache.py
sensemapi/client.py
sensemapi/compat.py
sensemapi/errors.py
sensemapi/heuristic.py
sensemapi/paths.py
sensemapi/reprobject.py
sensemapi/senseBox.py
sensemapi/senseBoxSensorData.py
sensemapi/sensor.py
sensemapi/utils.py
sensemapi/version.py
sensemapi/xdg.py
sensemapi.egg-info/PKG-INFO
sensemapi.egg-info/SOURCES.txt
sensemapi.egg-info/dependency_links.txt
sensemapi.egg-info/entry_points.txt
sensemapi.egg-info/requires.txt
sensemapi.egg-info/top_level.txt
sensemapi/cli/__init__.py
sensemapi/cli/__main__.py
sensemapi/cli/commands/__init__.py
sensemapi/cli/commands/download.py
sensemapi/cli/commands/main.py
sensemapi/cli/commands/route_mqtt/__init__.py
sensemapi/cli/commands/route_mqtt/client.py
sensemapi/cli/commands/route_mqtt/config.py
sensemapi/cli/commands/route_mqtt/queue.py