Metadata-Version: 2.1
Name: sensemapi
Version: 0.5.0
Summary: Pythonic access to the OpenSenseMap API
Home-page: https://gitlab.com/tue-umphy/co2mofetten/software/python3-sensemapi
Author: Yann Büchau
Author-email: nobodyinperson@gmx.de
License: GPLv3
Keywords: opensensemap,sensemap,api
Classifier: License :: OSI Approved :: GNU General Public License v3 (GPLv3)
Requires-Python: >=3.8
Provides-Extra: cache
Provides-Extra: mqtt
License-File: LICENSE
